delta_tracker/__init__.py
delta_tracker-0.2.dist-info/LICENSE.txt
delta_tracker-0.2.dist-info/METADATA
delta_tracker-0.2.dist-info/WHEEL
delta_tracker-0.2.dist-info/top_level.txt
delta_tracker-0.2.dist-info/RECORD
