Metadata-Version: 2.1
Name: delta-tracker
Version: 0.2
Summary: This is a audit tracking package
Home-page: UNKNOWN
Author: MADAM
License: UNKNOWN
Platform: UNKNOWN
Classifier: Programming Language :: Python :: 3
Classifier: License :: OSI Approved :: MIT License
Classifier: Operating System :: OS Independent
License-File: LICENSE.txt
Requires-Dist: pandas
Requires-Dist: fastavro
Requires-Dist: pyrebase
Requires-Dist: sweetviz
